mypackage/__init__.py
mypackage/__main__.py
mypackage/decorators.py
mypackage/descriptors.py
mypackage/generators.py
mypackage/iterators.py
mypackage/tests/__init__.py
mypackage/tests/test_decorators.py
mypackage/tests/test_descriptors.py
mypackage/tests/test_generators.py
mypackage/tests/test_iterators.py
mypackage_eaf27-1.0.dist-info/METADATA
mypackage_eaf27-1.0.dist-info/WHEEL
mypackage_eaf27-1.0.dist-info/entry_points.txt
mypackage_eaf27-1.0.dist-info/top_level.txt
mypackage_eaf27-1.0.dist-info/RECORD
