Metadata-Version: 2.1
Name: mypackage-eaf27
Version: 1.0
Summary: text
Author: qwertyqwerty
Author-email: eaf27@tpu.ru
Classifier: Programming Language :: Python :: 3
Classifier: License :: OSI Approved :: MIT License
Classifier: Operating System :: OS Independent
Requires-Python: >=3.6
